browsely/__init__.py
browsely/browser.py
browsely-0.0.1.dist-info/LICENSE
browsely-0.0.1.dist-info/METADATA
browsely-0.0.1.dist-info/WHEEL
browsely-0.0.1.dist-info/top_level.txt
browsely-0.0.1.dist-info/RECORD
