Metadata-Version: 2.2
Name: browsely
Version: 0.0.1
Summary: Intelligent AI Powered Web Browser Automation
Author-email: The Developer <developer@example.com>
Classifier: Intended Audience :: Developers
Classifier: License :: OSI Approved :: Apache Software License
Classifier: Operating System :: OS Independent
Classifier: Programming Language :: Python :: 3
Requires-Python: >=3.8
License-File: LICENSE
Requires-Dist: playwright
